comparisons/__init__.py
comparisons/compare_functions.py
comparisons-0.4.dist-info/METADATA
comparisons-0.4.dist-info/WHEEL
comparisons-0.4.dist-info/top_level.txt
comparisons-0.4.dist-info/RECORD
