Metadata-Version: 2.1
Name: comparisons
Version: 0.4
Summary: UNKNOWN
Home-page: UNKNOWN
Author: UNKNOWN
Author-email: UNKNOWN
License: UNKNOWN
Platform: UNKNOWN
Requires-Dist: pandas
Requires-Dist: numpy
Requires-Dist: regex
Requires-Dist: python-Levenshtein
